Metadata-Version: 2.1
Name: pythonqlib
Version: 0.9.3.99
Summary: A Quantitative-research Platform
License: MIT Licence
Classifier: Operating System :: POSIX :: Linux
Classifier: Operating System :: Microsoft :: Windows
Classifier: Operating System :: MacOS
Classifier: License :: OSI Approved :: MIT License
Classifier: Development Status :: 3 - Alpha
Classifier: Programming Language :: Python
Classifier: Programming Language :: Python :: 3
Classifier: Programming Language :: Python :: 3.7
Classifier: Programming Language :: Python :: 3.8
Classifier: Programming Language :: Python :: 3.9
Requires-Python: >=3.5.0
License-File: LICENSE
Requires-Dist: numpy <1.24,>=1.12.0
Requires-Dist: pandas >=0.25.1
Requires-Dist: scipy >=1.0.0
Requires-Dist: requests >=2.18.0
Requires-Dist: sacred >=0.7.4
Requires-Dist: python-socketio
Requires-Dist: redis >=3.0.1
Requires-Dist: python-redis-lock >=3.3.1
Requires-Dist: schedule >=0.6.0
Requires-Dist: cvxpy >=1.0.21
Requires-Dist: hyperopt ==0.1.2
Requires-Dist: fire >=0.3.1
Requires-Dist: statsmodels
Requires-Dist: xlrd >=1.0.0
Requires-Dist: plotly >=4.12.0
Requires-Dist: matplotlib >=3.3
Requires-Dist: tables >=3.6.1
Requires-Dist: pyyaml >=5.3.1
Requires-Dist: mlflow <=1.30.0,>=1.12.1
Requires-Dist: packaging <22
Requires-Dist: tqdm
Requires-Dist: loguru
Requires-Dist: lightgbm >=3.3.0
Requires-Dist: tornado
Requires-Dist: joblib >=0.17.0
Requires-Dist: ruamel.yaml <=0.17.36
Requires-Dist: pymongo ==3.7.2
Requires-Dist: scikit-learn >=0.22
Requires-Dist: dill
Requires-Dist: filelock
Requires-Dist: jinja2 <3.1.0
Requires-Dist: gym
Requires-Dist: cryptography
Requires-Dist: dataclasses ; python_version < "3.7"
Requires-Dist: protobuf <=3.20.1 ; python_version <= "3.8"
Provides-Extra: dev
Requires-Dist: coverage ; extra == 'dev'
Requires-Dist: pytest >=3 ; extra == 'dev'
Requires-Dist: sphinx ; extra == 'dev'
Requires-Dist: sphinx-rtd-theme ; extra == 'dev'
Requires-Dist: pre-commit ; extra == 'dev'
Requires-Dist: wheel ; extra == 'dev'
Requires-Dist: setuptools ; extra == 'dev'
Requires-Dist: black ; extra == 'dev'
Requires-Dist: pylint <=2.17.6 ; extra == 'dev'
Requires-Dist: mypy <0.981 ; extra == 'dev'
Requires-Dist: flake8 ; extra == 'dev'
Requires-Dist: nbqa ; extra == 'dev'
Requires-Dist: jupyter ; extra == 'dev'
Requires-Dist: nbconvert ; extra == 'dev'
Requires-Dist: importlib-metadata <5.0.0 ; extra == 'dev'
Requires-Dist: readthedocs-sphinx-ext ; extra == 'dev'
Requires-Dist: cmake ; extra == 'dev'
Requires-Dist: lxml ; extra == 'dev'
Requires-Dist: baostock ; extra == 'dev'
Requires-Dist: yahooquery ; extra == 'dev'
Requires-Dist: beautifulsoup4 ; extra == 'dev'
Requires-Dist: tianshou <=0.4.10 ; extra == 'dev'
Requires-Dist: gym >=0.24 ; extra == 'dev'
Provides-Extra: rl
Requires-Dist: tianshou <=0.4.10 ; extra == 'rl'
Requires-Dist: torch ; extra == 'rl'
